rdiff/__init__.py
rdiff/delta.py
rdiff/md4.py
rdiff/patch.py
rdiff/signature.py
rdiff-0.2.3.dist-info/LICENSE.txt
rdiff-0.2.3.dist-info/METADATA
rdiff-0.2.3.dist-info/WHEEL
rdiff-0.2.3.dist-info/top_level.txt
rdiff-0.2.3.dist-info/RECORD
