Metadata-Version: 2.1
Name: rdiff
Version: 0.2.3
Summary: A native python implementation of the rdiff tool by librsync
Home-page: https://github.com/MohitPanchariya/rdiff
Author: Mohit Panchariya
Author-email: iammohitpanchariya@gmail.com
Keywords: rdiff,librsync,native,python
Requires-Python: >=3.6
License-File: LICENSE.txt
